slfmri/__init__.py
slfmri/deprecated/__init__.py
slfmri/deprecated/methods.py
slfmri/deprecated/tmpobj.py
slfmri/lib/__init__.py
slfmri/lib/errors.py
slfmri/lib/utils.py
slfmri/lib/io/__init__.py
slfmri/lib/io/afni.py
slfmri/lib/io/itksnap.py
slfmri/lib/signal/__init__.py
slfmri/lib/signal/corr.py
slfmri/lib/signal/freq.py
slfmri/lib/signal/linalg.py
slfmri/lib/signal/norm.py
slfmri/lib/signal/qc.py
slfmri/lib/timeseries/__init__.py
slfmri/lib/timeseries/corr.py
slfmri/lib/timeseries/freq.py
slfmri/lib/timeseries/linalg.py
slfmri/lib/timeseries/norm.py
slfmri/lib/timeseries/qc.py
slfmri/lib/viz/__init__.py
slfmri/lib/viz/report.py
slfmri/lib/volume/__init__.py
slfmri/lib/volume/corr.py
slfmri/lib/volume/decomp.py
slfmri/lib/volume/man.py
slfmri/lib/volume/norm.py
slfmri/lib/volume/orient.py
slfmri/lib/volume/qc.py
slfmri/lib/volume/tools.py
slfmri/scripts/__init__.py
slfmri-0.0.7.dist-info/METADATA
slfmri-0.0.7.dist-info/WHEEL
slfmri-0.0.7.dist-info/top_level.txt
slfmri-0.0.7.dist-info/RECORD
