Metadata-Version: 2.1
Name: slfmri
Version: 0.0.7
Summary: Helper for fmri analysis for dvm-shlee
Home-page: https://github.com/dvm-shlee/slfmri
Author: SungHo Lee
Author-email: shlee@unc.edu
License: GNLv3
Keywords: personal helper
Platform: UNKNOWN
Classifier: Development Status :: 1 - Planning
Classifier: License :: OSI Approved :: GNU General Public License v3 (GPLv3)
Classifier: Natural Language :: English
Classifier: Operating System :: POSIX :: Linux
Classifier: Operating System :: MacOS
Classifier: Operating System :: Microsoft :: Windows :: Windows 10
Classifier: Programming Language :: Python :: 3.7
Classifier: Topic :: Software Development
Requires-Python: >3.5, <3.8
Requires-Dist: shleeh (>=0.0.4)
Requires-Dist: nibabel (>=3.0.2)
Requires-Dist: SimpleITK (>=1.2.4)
Requires-Dist: numpy (>=1.18.0)
Requires-Dist: pandas (>=1.0.0)
Requires-Dist: scipy (>=1.4.0)
Requires-Dist: scikit-learn (>=0.22.0)
